{"isNamespaced":false,"textureGroups":[{"atlases":[{"file":"atlas0.png","textures":[{"symbol":"ResearchCenter_spriteBackground","origin":[321.4,202.9],"rect":[1,1,643,406]},{"symbol":"CellsPanel_spriteBackground","origin":[314.85,47.9],"rect":[1,409,630,96]},{"symbol":"ResearchCenter_spriteXenoUpgrading","origin":[89.25,130.3],"rect":[633,409,178,261]},{"symbol":"_buttonCurseur_up","origin":[97.5,97.7],"rect":[646,1,196,196]},{"symbol":"_buttonInseminate_down","origin":[203.5,39.9],"rect":[1,507,407,80]},{"symbol":"_buttonInseminate_over","origin":[203.5,39.9],"rect":[1,589,407,80]},{"symbol":"_buttonFuse_up","origin":[203.5,39.9],"rect":[1,671,407,80]},{"symbol":"_buttonInseminate_up","origin":[203.5,39.9],"rect":[410,672,407,80]},{"symbol":"_buttonFuse_down","origin":[203.5,39.9],"rect":[1,753,407,80]},{"symbol":"_buttonFuse_over","origin":[203.5,39.9],"rect":[410,754,407,80]},{"symbol":"ResearchCenter_spriteXenoUnitBG","origin":[128.3,62.15],"rect":[1,835,257,125]},{"symbol":"_buttonMoins_over","origin":[96.4,47.4],"rect":[410,507,196,97]},{"symbol":"_buttonPlus_up","origin":[97.6,48.2],"rect":[646,199,196,97]},{"symbol":"_buttonMoins_up","origin":[96.1,48.25],"rect":[646,298,196,97]},{"symbol":"_buttonPlus_over","origin":[98.2,49.3],"rect":[813,397,196,97]},{"symbol":"_buttonCurseur_hit","origin":[67.5,67.5],"rect":[260,835,135,135]},{"symbol":"_buttonMoins_hit","origin":[67.5,67.5],"rect":[813,496,135,135]},{"symbol":"_buttonPlus_hit","origin":[67.5,67.5],"rect":[844,1,135,135]},{"symbol":"_buttonGene_Over","origin":[66.25,66.25],"rect":[844,138,133,133]},{"symbol":"_buttonGene_Hit","origin":[66.25,66.25],"rect":[819,633,133,133]},{"symbol":"_buttonGene_Down","origin":[66.25,66.25],"rect":[819,768,133,133]},{"symbol":"_buttonCell2_Hit","origin":[66.25,66.25],"rect":[397,836,133,133]},{"symbol":"_buttonCell2_Down","origin":[66.25,66.25],"rect":[532,836,133,133]},{"symbol":"_buttonCell2_Over","origin":[66.25,66.25],"rect":[667,836,133,133]},{"symbol":"ResearchCenter_spriteExperienceBg","origin":[17.5,131],"rect":[981,1,31,262]},{"symbol":"_buttonPlus_down","origin":[43,43],"rect":[844,273,86,86]},{"symbol":"_buttonCurseur_over","origin":[43,43],"rect":[932,273,86,86]},{"symbol":"_buttonCurseur_down","origin":[43,43],"rect":[802,903,86,86]},{"symbol":"_buttonMoins_down","origin":[43,43],"rect":[890,903,86,86]},{"symbol":"ResearchCenter_spriteCellQuantityBG","origin":[40.1,31.6],"rect":[410,606,80,59]},{"symbol":"_buttonFleche_down","origin":[32.6,29.1],"rect":[492,606,66,58]},{"symbol":"_buttonFleche_up","origin":[28.5,32.5],"rect":[950,496,58,66]},{"symbol":"_buttonFleche_over","origin":[18.75,16.75],"rect":[560,606,38,33]},{"symbol":"txt_CellsResearchDisplay","data":{"y":-15.85,"text":"XXX","x":-37.9,"width":75.8,"font":"25px Times New Roman","align":"center","height":31.7,"wordWrap":1,"color":"#FFFFFF"},"baseClass":"TextSprite","origin":[0,0],"rect":[813,633,1,1]},{"symbol":"txt_Fuse","data":{"y":-48.45,"text":"Fuse","x":-162.55,"width":323.1,"font":"72px Arial","align":"center","height":93.15,"wordWrap":1,"color":"#000000"},"baseClass":"TextSprite","origin":[0,0],"rect":[816,633,1,1]},{"symbol":"txt_inseminate","data":{"y":-53.05,"text":"Start researching","x":-325.8,"width":651.6,"font":"80px Arial","align":"center","height":106.1,"wordWrap":1,"color":"#000000"},"baseClass":"TextSprite","origin":[0,0],"rect":[813,636,1,1]},{"symbol":"txt_skip","data":{"y":-53.05,"text":"Skip","x":-152,"width":298.5,"font":"80px Arial","align":"center","height":95.3,"wordWrap":1,"color":"#000000"},"baseClass":"TextSprite","origin":[0,0],"rect":[816,636,1,1]},{"symbol":"txt_timer","data":{"y":-35.75,"text":"< x h xx min >","x":-226.35,"width":432.6,"font":"60px Arial","align":"center","height":61.75,"wordWrap":1,"color":"#000000"},"baseClass":"TextSprite","origin":[0,0],"rect":[813,639,1,1]},{"symbol":"txt_xenoName","data":{"y":-30.3,"text":"Schema Name","x":-142.4,"width":341.15,"font":"50px Arial","align":"left","height":59.85,"wordWrap":0,"color":"#FFFFFF"},"baseClass":"TextSprite","origin":[0,0],"rect":[816,639,1,1]}]},{"file":"atlas1.png","textures":[{"symbol":"_buttonCell2_up","origin":[66.25,66.25],"rect":[1,1,133,133]},{"symbol":"_buttonGene_up","origin":[66.25,66.25],"rect":[1,136,133,133]},{"symbol":"_buttonSkipUpgradeCenter_up","origin":[131.2,29.5],"rect":[1,271,263,60]},{"symbol":"_buttonSkipUpgradeCenter_over","origin":[130.8,29.8],"rect":[1,333,263,60]},{"symbol":"_buttonSkipUpgradeCenter_down","origin":[131.8,30.15],"rect":[1,395,263,60]},{"symbol":"ResearchCenter_spriteXenoAvatar","origin":[40.4,44],"rect":[136,1,81,89]}]}],"scaleFactor":1}],"movies":[{"layers":[{"keyframes":[{"data":{"UIPosition_Desktop":"right","UIPosition":"right"},"pivot":[314.85,47.9],"tweened":false,"loc":[-6.175,294.7],"index":0,"ref":"CellsPanel_spriteBackground","duration":1}],"name":"CellsPanel_spriteBackground"},{"keyframes":[{"data":{"UIPosition_Desktop":"right","UIPosition":"right"},"tweened":false,"loc":[197.6,275],"scale":[0.6716,0.4618],"index":0,"ref":"~btn_Fuse","duration":1}],"name":"btn_Fuse"},{"keyframes":[{"data":{"UIPosition_Desktop":"right","UIPosition":"right"},"tweened":false,"loc":[65.1,316],"scale":[0.3698,0.2099],"index":0,"ref":"~btn_Cell2","duration":1}],"name":"btn_Cell2 #9"},{"keyframes":[{"data":{"UIPosition_Desktop":"right","UIPosition":"right"},"tweened":false,"loc":[-18.9,316],"scale":[0.3698,0.2099],"index":0,"ref":"~btn_Cell2","duration":1}],"name":"btn_Cell2 #8"},{"keyframes":[{"data":{"UIPosition_Desktop":"right","UIPosition":"right"},"tweened":false,"loc":[-102.9,316],"scale":[0.3698,0.2099],"index":0,"ref":"~btn_Cell2","duration":1}],"name":"btn_Cell2 #7"},{"keyframes":[{"data":{"UIPosition_Desktop":"right","UIPosition":"right"},"tweened":false,"loc":[-185.4,316],"scale":[0.3698,0.2099],"index":0,"ref":"~btn_Cell2","duration":1}],"name":"btn_Cell2 #6"},{"keyframes":[{"data":{"UIPosition_Desktop":"right","UIPosition":"right"},"tweened":false,"loc":[-267.4,316],"scale":[0.3698,0.2099],"index":0,"ref":"~btn_Cell2","duration":1}],"name":"btn_Cell2 #5"},{"keyframes":[{"data":{"UIPosition_Desktop":"right","UIPosition":"right"},"tweened":false,"loc":[-267.4,274.5],"scale":[0.3698,0.2099],"index":0,"ref":"~btn_Cell2","duration":1}],"name":"btn_Cell2 #4"},{"keyframes":[{"data":{"UIPosition_Desktop":"right","UIPosition":"right"},"tweened":false,"loc":[-185.4,274.5],"scale":[0.3698,0.2099],"index":0,"ref":"~btn_Cell2","duration":1}],"name":"btn_Cell2 #3"},{"keyframes":[{"data":{"UIPosition_Desktop":"right","UIPosition":"right"},"tweened":false,"loc":[-102.9,274.5],"scale":[0.3698,0.2099],"index":0,"ref":"~btn_Cell2","duration":1}],"name":"btn_Cell2 #2"},{"keyframes":[{"data":{"UIPosition_Desktop":"right","UIPosition":"right"},"tweened":false,"loc":[-18.9,274.5],"scale":[0.3698,0.2099],"index":0,"ref":"~btn_Cell2","duration":1}],"name":"btn_Cell2 #1"},{"keyframes":[{"data":{"UIPosition_Desktop":"right","UIPosition":"right"},"tweened":false,"loc":[64.1,274.5],"scale":[0.3698,0.2099],"index":0,"ref":"~btn_Cell2","duration":1}],"name":"btn_Cell2"},{"keyframes":[{"data":{"UIPosition_Desktop":"right","UIPosition":"right"},"pivot":[321.425,202.9],"tweened":false,"loc":[-111.025,5.9],"scale":[1.1653,1],"index":0,"ref":"ResearchCenter_spriteBackground","duration":1}],"name":"ResearchCenter_spriteBackground"},{"keyframes":[{"data":{"UIPosition_Desktop":"right","UIPosition":"right"},"tweened":false,"loc":[-38.425,-35.925],"index":0,"ref":"~ResearchCenter_clipXenoListUpgrading","duration":1}],"name":"ResearchCenter_clipXenoListUpgrading"},{"keyframes":[{"data":{"UIPosition_Desktop":"right","UIPosition":"right"},"tweened":false,"duration":1,"loc":[10.55,-36.975],"scale":[0.307,0.307],"index":0,"ref":"~btn_Curseur","skew":[-3.1416,3.1416]}],"name":"btn_Curseur #2"},{"keyframes":[{"data":{"UIPosition_Desktop":"right","UIPosition":"right"},"tweened":false,"duration":1,"loc":[184.55,-36.975],"scale":[0.307,0.307],"index":0,"ref":"~btn_Curseur","skew":[-3.1416,3.1416]}],"name":"btn_Curseur #1"},{"keyframes":[{"data":{"UIPosition_Desktop":"right","UIPosition":"right"},"tweened":false,"duration":1,"loc":[184.6,-170.5],"scale":[0.307,0.307],"index":0,"ref":"~btn_Plus","skew":[-3.1416,3.1416]}],"name":"btn_Plus #2"},{"keyframes":[{"data":{"UIPosition_Desktop":"right","UIPosition":"right"},"tweened":false,"duration":1,"loc":[-168,91.55],"scale":[0.307,0.307],"index":0,"ref":"~btn_Moins","skew":[-3.1416,3.1416]}],"name":"btn_Moins #2"},{"keyframes":[{"data":{"UIPosition_Desktop":"right","UIPosition":"right"},"tweened":false,"duration":1,"loc":[11.1,91.5],"scale":[0.307,0.307],"index":0,"ref":"~btn_Moins","skew":[-3.1416,3.1416]}],"name":"btn_Moins #1"},{"keyframes":[{"data":{"UIPosition_Desktop":"right","UIPosition":"right"},"tweened":false,"duration":1,"loc":[185.1,91.5],"scale":[0.307,0.307],"index":0,"ref":"~btn_Moins","skew":[-3.1416,3.1416]}],"name":"btn_Moins"},{"keyframes":[{"data":{"UIPosition_Desktop":"right","UIPosition":"right"},"tweened":false,"duration":1,"loc":[-166.85,-36.975],"scale":[0.307,0.307],"index":0,"ref":"~btn_Curseur","skew":[-3.1416,3.1416]}],"name":"btn_Curseur"},{"keyframes":[{"data":{"UIPosition_Desktop":"right","UIPosition":"right"},"tweened":false,"duration":1,"loc":[-168.1,-166.525],"scale":[0.307,0.307],"index":0,"ref":"~btn_Plus","skew":[-3.1416,3.1416]}],"name":"btn_Plus #1"},{"keyframes":[{"data":{"UIPosition_Desktop":"right","UIPosition":"right"},"tweened":false,"duration":1,"loc":[10.6,-170],"scale":[0.307,0.307],"index":0,"ref":"~btn_Plus","skew":[-3.1416,3.1416]}],"name":"btn_Plus"},{"keyframes":[{"data":{"UIPosition_Desktop":"right","UIPosition":"right"},"tweened":false,"loc":[-396.125,6.375],"index":0,"ref":"~ResearchCenter_clipXenoList","duration":1}],"name":"ResearchCenter_clipXenoList"},{"keyframes":[{"data":{"UIPosition_Desktop":"right","UIPosition":"right"},"tweened":false,"loc":[-47.025,164.625],"scale":[0.6833,0.6833],"index":0,"ref":"~btn_Inseminate","duration":1}],"name":"btn_Inseminate"},{"keyframes":[{"data":{"UIPosition_Desktop":"right","UIPosition":"right"},"tweened":false,"loc":[-45.45,170.95],"scale":[0.9233,0.8525],"index":0,"ref":"~btn_SkipUpgradeCenter","duration":1}],"name":"btn_SkipUpgradeCenter"},{"keyframes":[{"data":{"UIPosition_Desktop":"right","UIPosition":"right"},"tweened":false,"loc":[-40.5,130.75],"index":0,"ref":"txt_timer","duration":1}],"name":"txt_timer"},{"keyframes":[{"data":{"UIPosition_Desktop":"right","UIPosition":"right"},"tweened":false,"loc":[-392.5,-176.25],"index":0,"ref":"~btn_Fleche","duration":1}],"name":"btn_Fleche #1"},{"keyframes":[{"data":{"UIPosition_Desktop":"right","UIPosition":"right"},"tweened":false,"duration":1,"loc":[-392.5,190.75],"index":0,"ref":"~btn_Fleche","skew":[-3.1416,3.1416]}],"name":"btn_Fleche"}],"id":"ResearchCenter"},{"layers":[{"keyframes":[{"pivot":[40.1,31.6],"tweened":false,"loc":[0.8,1.325],"scale":[0.5434,0.5434],"index":0,"ref":"ResearchCenter_spriteCellQuantityBG","duration":1}],"name":"ResearchCenter_spriteCellQuantityBG"},{"keyframes":[{"loc":[-3.2,-0.175],"tweened":false,"index":0,"ref":"txt_CellsResearchDisplay","duration":1}],"name":"txt_CellsResearchDisplay"}],"id":"~ResearchCenter_clipCellQuantity"},{"layers":[{"keyframes":[{"pivot":[17.675,131.325],"tweened":false,"loc":[25.5,0],"index":0,"ref":"ResearchCenter_spriteExperienceBg","duration":1}],"name":"ResearchCenter_spriteExperienceBg"},{"keyframes":[{"loc":[-19.975,0.25],"tweened":false,"index":0,"ref":"~ResearchCenter_clipCellQuantity","duration":1}],"name":"ResearchCenter_clipCellQuantity"}],"id":"~ResearchCenter_clipExperience"},{"layers":[{"keyframes":[{"loc":[0.7,-65.5],"tweened":false,"index":0,"ref":"~ResearchCenter_clipXenoUnit","duration":1}],"name":"UpgradeCenter_clipXenoUnit"},{"keyframes":[{"loc":[0.7,1.725],"tweened":false,"index":0,"ref":"~ResearchCenter_clipXenoUnit","duration":1}],"name":"UpgradeCenter_clipXenoUnit"},{"keyframes":[{"loc":[0.7,69.85],"tweened":false,"index":0,"ref":"~ResearchCenter_clipXenoUnit","duration":1}],"name":"UpgradeCenter_clipXenoUnit"},{"keyframes":[{"loc":[0.7,137.775],"tweened":false,"index":0,"ref":"~ResearchCenter_clipXenoUnit","duration":1}],"name":"UpgradeCenter_clipXenoUnit"},{"keyframes":[{"loc":[0.7,-132.225],"tweened":false,"index":0,"ref":"~ResearchCenter_clipXenoUnit","duration":1}],"name":"UpgradeCenter_clipXenoUnit"}],"id":"~ResearchCenter_clipXenoList"},{"layers":[{"keyframes":[{"loc":[-174.625,-1.05],"tweened":false,"index":0,"ref":"~ResearchCenter_clipXenoUnitUpgrading","duration":1}],"name":"ResearchCenter_clipXenoUnitUpgrading #2"},{"keyframes":[{"loc":[0.975,-1.05],"tweened":false,"index":0,"ref":"~ResearchCenter_clipXenoUnitUpgrading","duration":1}],"name":"ResearchCenter_clipXenoUnitUpgrading #1"},{"keyframes":[{"loc":[176.2,-1.05],"tweened":false,"index":0,"ref":"~ResearchCenter_clipXenoUnitUpgrading","duration":1}],"name":"ResearchCenter_clipXenoUnitUpgrading"}],"id":"~ResearchCenter_clipXenoListUpgrading"},{"layers":[{"keyframes":[{"pivot":[128.3,62.15],"tweened":false,"loc":[-0.7,-0.1],"scale":[0.5602,0.4716],"index":0,"ref":"ResearchCenter_spriteXenoUnitBG","duration":1}],"name":"UpgradeCenter_spriteXenoUnitBG"},{"keyframes":[{"pivot":[40.375,44.025],"tweened":false,"loc":[-0.325,8.775],"scale":[1.4697,0.3871],"index":0,"ref":"ResearchCenter_spriteXenoAvatar","duration":1}],"name":"UpgradeCenter_spriteXenoAvatar"},{"keyframes":[{"tweened":false,"loc":[-8.225,-20.775],"scale":[0.5852,0.5852],"index":0,"ref":"txt_xenoName","duration":1}],"name":"txt_xenoName"}],"id":"~ResearchCenter_clipXenoUnit"},{"layers":[{"keyframes":[{"pivot":[89.25,130.325],"tweened":false,"loc":[0.325,-0.65],"scale":[0.7359,1.1001],"index":0,"ref":"ResearchCenter_spriteXenoUpgrading","duration":1}],"name":"ResearchCenter_spriteXenoUpgrading"},{"keyframes":[{"loc":[25.5,-0.7],"tweened":false,"index":0,"ref":"~ResearchCenter_clipExperience","duration":1}],"name":"ResearchCenter_clipExperience"}],"id":"~ResearchCenter_clipXenoUnitUpgrading"},{"baseClass":"flash.display.SimpleButton","layers":[{"keyframes":[{"pivot":[66.25,66.25],"index":0,"ref":"_buttonCell2_up","tweened":false,"duration":1},{"pivot":[66.25,66.25],"index":1,"ref":"_buttonCell2_Over","tweened":false,"duration":1},{"pivot":[66.25,66.25],"index":2,"ref":"_buttonCell2_Down","tweened":false,"duration":1},{"pivot":[66.25,66.25],"index":3,"ref":"_buttonCell2_Hit","tweened":false,"duration":1}],"name":"Calque 1"}],"id":"~btn_Cell2"},{"baseClass":"flash.display.SimpleButton","layers":[{"keyframes":[{"pivot":[97.5,97.675],"index":0,"ref":"_buttonCurseur_up","tweened":false,"duration":1},{"pivot":[42.975,42.975],"tweened":false,"loc":[-0.8,-0.2],"scale":[2.0671,2.0671],"index":1,"ref":"_buttonCurseur_over","duration":1},{"pivot":[42.975,42.975],"tweened":false,"loc":[-0.625,-1.075],"scale":[2.1585,2.1195],"index":2,"ref":"_buttonCurseur_down","duration":1},{"pivot":[67.5,67.5],"tweened":false,"loc":[-0.725,-0.525],"index":3,"ref":"_buttonCurseur_hit","duration":1}],"name":"Layer 1"}],"id":"~btn_Curseur"},{"baseClass":"flash.display.SimpleButton","layers":[{"keyframes":[{"pivot":[28.475,32.525],"tweened":false,"duration":1,"scale":[0.5404,0.5404],"index":0,"ref":"_buttonFleche_up","skew":[-1.5708,-1.5708]},{"pivot":[18.775,16.425],"tweened":false,"loc":[-0.075,-0.75],"index":1,"ref":"_buttonFleche_over","duration":1},{"pivot":[32.65,28.8],"tweened":false,"loc":[-0.1555,-0.3028],"scale":[0.5928,0.5928],"index":2,"ref":"_buttonFleche_down","duration":2}],"name":"Calque 1"}],"id":"~btn_Fleche"},{"baseClass":"flash.display.SimpleButton","layers":[{"keyframes":[{"pivot":[203.525,39.875],"tweened":false,"loc":[-0.975,-0.5],"scale":[0.4028,1],"index":0,"ref":"_buttonFuse_up","duration":1},{"pivot":[203.525,39.875],"tweened":false,"loc":[0.025,0],"scale":[0.4004,1],"index":1,"ref":"_buttonFuse_over","duration":1},{"pivot":[203.525,39.875],"tweened":false,"loc":[0.025,0],"scale":[0.4029,1],"index":2,"ref":"_buttonFuse_down","duration":2}],"name":"_buttonContinue"},{"keyframes":[{"loc":[-1,-0.575],"tweened":false,"index":0,"ref":"txt_Fuse","duration":4}],"name":"txt_Destroy"}],"id":"~btn_Fuse"},{"baseClass":"flash.display.SimpleButton","layers":[{"keyframes":[{"pivot":[203.525,39.875],"tweened":false,"loc":[-0.475,-0.5],"index":0,"ref":"_buttonInseminate_up","duration":1},{"pivot":[203.5,39.875],"tweened":false,"loc":[-0.4,-0.875],"index":1,"ref":"_buttonInseminate_over","duration":1},{"pivot":[203.5,39.875],"tweened":false,"loc":[-1,-0.95],"index":2,"ref":"_buttonInseminate_down","duration":1},{"pivot":[203.5,39.875],"tweened":false,"loc":[-0.875,-0.85],"index":3,"ref":"_buttonInseminate_down","duration":1}],"name":"button"},{"keyframes":[{"loc":[-0.5,-0.5],"tweened":false,"index":0,"ref":"txt_inseminate","duration":3},{"index":3,"duration":1}],"name":"txt_Inseminate"}],"id":"~btn_Inseminate"},{"baseClass":"flash.display.SimpleButton","layers":[{"keyframes":[{"pivot":[96.075,48.25],"index":0,"ref":"_buttonMoins_up","tweened":false,"duration":1},{"pivot":[96.4,47.4],"tweened":false,"loc":[-0.8,-0.2],"scale":[0.9655,0.9655],"index":1,"ref":"_buttonMoins_over","duration":1},{"pivot":[42.975,42.975],"tweened":false,"loc":[-0.625,-1.075],"scale":[2.1585,2.1195],"index":2,"ref":"_buttonMoins_down","duration":1},{"pivot":[67.5,67.5],"tweened":false,"loc":[-0.725,-0.525],"scale":[1.3585,0.57],"index":3,"ref":"_buttonMoins_hit","duration":1}],"name":"Layer 1"}],"id":"~btn_Moins"},{"baseClass":"flash.display.SimpleButton","layers":[{"keyframes":[{"pivot":[97.575,48.225],"index":0,"ref":"_buttonPlus_up","tweened":false,"duration":1},{"pivot":[98.175,49.325],"tweened":false,"loc":[-0.8,-0.2],"scale":[0.9655,0.9655],"index":1,"ref":"_buttonPlus_over","duration":1},{"pivot":[42.975,42.975],"tweened":false,"loc":[-0.625,-1.075],"scale":[2.1585,2.1195],"index":2,"ref":"_buttonPlus_down","duration":1},{"pivot":[67.5,67.5],"tweened":false,"loc":[-0.725,-0.525],"scale":[1.3585,0.57],"index":3,"ref":"_buttonPlus_hit","duration":1}],"name":"Layer 1"}],"id":"~btn_Plus"},{"baseClass":"flash.display.SimpleButton","layers":[{"keyframes":[{"pivot":[131.225,29.475],"tweened":false,"loc":[-0.475,-0.5],"index":0,"ref":"_buttonSkipUpgradeCenter_up","duration":1},{"pivot":[130.8,29.775],"tweened":false,"loc":[-0.375,-0.875],"index":1,"ref":"_buttonSkipUpgradeCenter_over","duration":1},{"pivot":[131.8,30.15],"tweened":false,"loc":[-0.975,-0.95],"index":2,"ref":"_buttonSkipUpgradeCenter_down","duration":1},{"pivot":[131.8,30.15],"tweened":false,"loc":[-0.85,-0.85],"index":3,"ref":"_buttonSkipUpgradeCenter_down","duration":1}],"name":"button"},{"keyframes":[{"loc":[-0.5,3],"tweened":false,"index":0,"ref":"txt_skip","duration":3},{"index":3,"duration":1}],"name":"txt_Skip"}],"id":"~btn_SkipUpgradeCenter"}],"md5":"36fb9f60d5e4dcbdf9584fa232cb35da","frameRate":24}