{
 "isNamespaced": false,
 "textureGroups": [
  {
   "atlases": [
    {
     "file": "atlas0.png",
     "textures": [
      {
       "symbol": "Deplacement_buttonYes_Down",
       "origin": [
        91.7,
        86
       ],
       "rect": [
        1,
        1,
        184,
        173
       ]
      },
      {
       "symbol": "Deplacement_buttonNo_Over",
       "origin": [
        91.65,
        86
       ],
       "rect": [
        187,
        1,
        184,
        173
       ]
      },
      {
       "symbol": "Deplacement_buttonNo_up",
       "origin": [
        91.65,
        86.05
       ],
       "rect": [
        1,
        176,
        184,
        173
       ]
      },
      {
       "symbol": "Deplacement_buttonNo_Down",
       "origin": [
        91.65,
        86.05
       ],
       "rect": [
        187,
        176,
        184,
        173
       ]
      },
      {
       "symbol": "Deplacement_buttonYes_Over",
       "origin": [
        91.7,
        86
       ],
       "rect": [
        1,
        351,
        184,
        173
       ]
      },
      {
       "symbol": "Deplacement_buttonYes_up",
       "origin": [
        91.7,
        86
       ],
       "rect": [
        187,
        351,
        184,
        173
       ]
      }
     ]
    }
   ],
   "scaleFactor": 1
  }
 ],
 "movies": [
  {
   "layers": [
    {
     "keyframes": [
      {
       "loc": [
        586.575,
        -86.8125
       ],
       "tweened": false,
       "index": 0,
       "ref": "~Deplacement_btn_Yes",
       "duration": 1
      }
     ],
     "name": "btn_Yes"
    },
    {
     "keyframes": [
      {
       "data": {
        "UIPosition": "bottom"
       },
       "pivot": [
        0,
        -0.075
       ],
       "tweened": false,
       "loc": [
        5.1375,
        357
       ],
       "index": 0,
       "ref": "~Deplacement_btn_No",
       "duration": 1
      }
     ],
     "name": "btn_No"
    }
   ],
   "id": "Deplacement"
  },
  {
   "baseClass": "flash.display.SimpleButton",
   "layers": [
    {
     "keyframes": [
      {
       "pivot": [
        91.65,
        86.025
       ],
       "tweened": false,
       "loc": [
        0,
        -0.0375
       ],
       "index": 0,
       "ref": "Deplacement_buttonNo_up",
       "duration": 1
      },
      {
       "pivot": [
        91.65,
        86.025
       ],
       "index": 1,
       "ref": "Deplacement_buttonNo_Over",
       "tweened": false,
       "duration": 1
      },
      {
       "pivot": [
        91.65,
        86.025
       ],
       "tweened": false,
       "loc": [
        0,
        -0.0431
       ],
       "scale": [
        1.15,
        1.15
       ],
       "index": 2,
       "ref": "Deplacement_buttonNo_Down",
       "duration": 1
      },
      {
       "pivot": [
        91.65,
        86.025
       ],
       "tweened": false,
       "loc": [
        0,
        -0.0375
       ],
       "index": 3,
       "ref": "Deplacement_buttonNo_Down",
       "duration": 1
      }
     ],
     "name": "Calque 1"
    }
   ],
   "id": "~Deplacement_btn_No"
  },
  {
   "baseClass": "flash.display.SimpleButton",
   "layers": [
    {
     "keyframes": [
      {
       "pivot": [
        91.65,
        86.025
       ],
       "tweened": false,
       "loc": [
        -0.0375,
        0
       ],
       "index": 0,
       "ref": "Deplacement_buttonYes_up",
       "duration": 1
      },
      {
       "pivot": [
        91.65,
        86.025
       ],
       "tweened": false,
       "loc": [
        -0.0375,
        0
       ],
       "index": 1,
       "ref": "Deplacement_buttonYes_Over",
       "duration": 1
      },
      {
       "pivot": [
        91.65,
        86.025
       ],
       "tweened": false,
       "loc": [
        -0.0431,
        0
       ],
       "scale": [
        1.15,
        1.15
       ],
       "index": 2,
       "ref": "Deplacement_buttonYes_Down",
       "duration": 1
      },
      {
       "pivot": [
        91.65,
        86.025
       ],
       "tweened": false,
       "loc": [
        -0.0375,
        0
       ],
       "index": 3,
       "ref": "Deplacement_buttonYes_up",
       "duration": 1
      }
     ],
     "name": "Layer 1"
    }
   ],
   "id": "~Deplacement_btn_Yes"
  }
 ],
 "md5": "d9261d9283eef7775fcc7ed0aabd81de",
 "frameRate": 24
}